adb_logging/__init__.py
adb_logging/pipelines.py
adb_logging-0.0.0.dist-info/METADATA
adb_logging-0.0.0.dist-info/WHEEL
adb_logging-0.0.0.dist-info/top_level.txt
adb_logging-0.0.0.dist-info/RECORD
