Metadata-Version: 2.1
Name: adb-logging
Version: 0.0.0
Summary: adb-logging package
Home-page: UNKNOWN
License: MIT
Platform: UNKNOWN
Classifier: License :: OSI Approved :: MIT License
Classifier: Programming Language :: Python :: 3
Classifier: Programming Language :: Python :: 3.7
